pynxtools_spm/__init__.py
pynxtools_spm/reader.py
pynxtools_spm/app/__init__.py
pynxtools_spm/configs/__init__.py
pynxtools_spm/configs/nanonis/nanonis_dat_generic_sts.json
pynxtools_spm/configs/nanonis/nanonis_sxm_generic_afm.json
pynxtools_spm/configs/nanonis/nanonis_sxm_generic_stm.json
pynxtools_spm/configs/omicron/omicron_sm4_stm.json
pynxtools_spm/nomad/entrypoints.py
pynxtools_spm/nomad/nomad_example_paths.py
pynxtools_spm/nomad/examples/afm/AFMExampleWithCustomization/A151216.123306-02602.sxm
pynxtools_spm/nomad/examples/afm/AFMExampleWithCustomization/AFMExample.archive.json
pynxtools_spm/nomad/examples/afm/AFMExampleWithCustomization/README.md
pynxtools_spm/nomad/examples/afm/AFMExampleWithCustomization/afm.scheme.archive.yaml
pynxtools_spm/nomad/examples/afm/AFMExampleWithCustomization/config.json
pynxtools_spm/nomad/examples/stm/STMExampleWithCustomization/Au_mica_2023_Y_A_diPAMY_195.sxm
pynxtools_spm/nomad/examples/stm/STMExampleWithCustomization/README.md
pynxtools_spm/nomad/examples/stm/STMExampleWithCustomization/STMExample.archive.json
pynxtools_spm/nomad/examples/stm/STMExampleWithCustomization/config.json
pynxtools_spm/nomad/examples/stm/STMExampleWithCustomization/stm.scheme.archive.yaml
pynxtools_spm/nomad/examples/sts/STSExampleWithCustomization/Bias-Spectroscopy00015_20230420.dat
pynxtools_spm/nomad/examples/sts/STSExampleWithCustomization/README.md
pynxtools_spm/nomad/examples/sts/STSExampleWithCustomization/STSExample.archive.json
pynxtools_spm/nomad/examples/sts/STSExampleWithCustomization/config.json
pynxtools_spm/nomad/examples/sts/STSExampleWithCustomization/sts.scheme.archive.yaml
pynxtools_spm/nxformatters/__init__.py
pynxtools_spm/nxformatters/base_formatter.py
pynxtools_spm/nxformatters/helpers.py
pynxtools_spm/nxformatters/nanonis/__init__.py
pynxtools_spm/nxformatters/nanonis/nanonis_base.py
pynxtools_spm/nxformatters/nanonis/nanonis_dat_sts.py
pynxtools_spm/nxformatters/nanonis/nanonis_sxm_afm.py
pynxtools_spm-0.2.2.dist-info/licenses/LICENSE
pynxtools_spm-0.2.2.dist-info/METADATA
pynxtools_spm-0.2.2.dist-info/WHEEL
pynxtools_spm-0.2.2.dist-info/entry_points.txt
pynxtools_spm-0.2.2.dist-info/top_level.txt
pynxtools_spm-0.2.2.dist-info/RECORD
