Metadata-Version: 2.4
Name: pynxtools-spm
Version: 0.2.2
Summary: pynxtools-spm: A pynxtools plugin for SPM (Scanning Probe Microscopy) data readers
Author: The NOMAD Authors
License: 
Project-URL: Homepage, https://github.com/FAIRmat-NFDI/pynxtools-spm
Project-URL: Parent Project, https://github.com/FAIRmat-NFDI
Classifier: Programming Language :: Python :: 3.10
Classifier: Programming Language :: Python :: 3.11
Classifier: Programming Language :: Python :: 3.12
Classifier: Programming Language :: Python :: 3.13
Classifier: License :: OSI Approved :: Apache Software License
Classifier: Operating System :: OS Independent
Requires-Python: >=3.10
License-File: LICENSE
Requires-Dist: pynxtools>=0.12.0
Requires-Dist: findiff>=0.11.1
Requires-Dist: matplotlib
Requires-Dist: scipy
Requires-Dist: hvplot
Requires-Dist: spym>=0.9.2
Requires-Dist: tzlocal
Provides-Extra: dev
Requires-Dist: mypy; extra == "dev"
Requires-Dist: ruff>=0.14.0; extra == "dev"
Requires-Dist: pytest; extra == "dev"
Requires-Dist: pre-commit; extra == "dev"
Provides-Extra: docs
Requires-Dist: mkdocs; extra == "docs"
Requires-Dist: mkdocs-mermaid2-plugin; extra == "docs"
Requires-Dist: mkdocstrings; extra == "docs"
Requires-Dist: mkdocs-material; extra == "docs"
Requires-Dist: mkdocs-macros-plugin; extra == "docs"
Requires-Dist: mkdocs-simple-hooks; extra == "docs"
Dynamic: license-file
